findly/__init__.py
findly/unified_reporting_sdk/__init__.py
findly/unified_reporting_sdk/data_sources/__init__.py
findly/unified_reporting_sdk/data_sources/common/__init__.py
findly/unified_reporting_sdk/data_sources/common/common_parser.py
findly/unified_reporting_sdk/data_sources/common/date_range_helper.py
findly/unified_reporting_sdk/data_sources/common/entities.py
findly/unified_reporting_sdk/data_sources/common/reports_client.py
findly/unified_reporting_sdk/data_sources/common/where_string_comparison.py
findly/unified_reporting_sdk/data_sources/fb_ads/__init__.py
findly/unified_reporting_sdk/data_sources/fb_ads/fb_ads_client.py
findly/unified_reporting_sdk/data_sources/fb_ads/fb_ads_query_args_parser.py
findly/unified_reporting_sdk/data_sources/fb_ads/metadata/action_breakdowns.csv
findly/unified_reporting_sdk/data_sources/fb_ads/metadata/breakdowns.csv
findly/unified_reporting_sdk/data_sources/fb_ads/metadata/dimensions.jsonl
findly/unified_reporting_sdk/data_sources/fb_ads/metadata/fields.csv
findly/unified_reporting_sdk/data_sources/fb_ads/metadata/metrics.jsonl
findly/unified_reporting_sdk/data_sources/ga4/__init__.py
findly/unified_reporting_sdk/data_sources/ga4/ga4_client.py
findly/unified_reporting_sdk/data_sources/ga4/ga4_query_args_parser.py
findly/unified_reporting_sdk/data_sources/ga4/metadata/dimensions.jsonl
findly/unified_reporting_sdk/data_sources/gsc/__init__.py
findly/unified_reporting_sdk/data_sources/gsc/gsc_client.py
findly/unified_reporting_sdk/data_sources/gsc/gsc_service.py
findly/unified_reporting_sdk/protos/.gitignore
findly/unified_reporting_sdk/protos/__init__.py
findly/unified_reporting_sdk/protos/findly_semantic_layer_pb2.py
findly/unified_reporting_sdk/protos/findly_semantic_layer_pb2.pyi
findly/unified_reporting_sdk/urs.py
findly_unified_reporting_sdk-0.7.14.dist-info/LICENSE
findly_unified_reporting_sdk-0.7.14.dist-info/METADATA
findly_unified_reporting_sdk-0.7.14.dist-info/WHEEL
findly_unified_reporting_sdk-0.7.14.dist-info/RECORD
