Metadata-Version: 2.1
Name: findly.unified-reporting-sdk
Version: 0.7.14
Summary: 
License: GPL-3.0-only
Requires-Python: >=3.9,<4.0
Classifier: License :: OSI Approved :: GNU General Public License v3 (GPLv3)
Classifier: Programming Language :: Python :: 3
Classifier: Programming Language :: Python :: 3.9
Classifier: Programming Language :: Python :: 3.10
Classifier: Programming Language :: Python :: 3.11
Classifier: Programming Language :: Python :: 3.12
Classifier: Programming Language :: Python :: 3.13
Requires-Dist: aiocache (>=0.12.2,<0.13.0)
Requires-Dist: backoff (>=2.2.1,<3.0.0)
Requires-Dist: facebook-business (>=22.0.5,<23.0.0)
Requires-Dist: google-analytics-admin (>=0.24.0,<0.25.0)
Requires-Dist: google-analytics-data (>=0.18.18,<0.19.0)
Requires-Dist: google-api-python-client (>=2.169.0,<3.0.0)
Requires-Dist: oauth2client (>=4.1.3,<5.0.0)
Requires-Dist: pandas (>=2.2.3,<3.0.0)
Requires-Dist: protobuf (>=4.25.3,<5.0.0)
Requires-Dist: sqlglot (>=26.17.1,<27.0.0)
